README.txt
TODO.txt
setup.py
docs/HISTORY.txt
docs/INSTALL.txt
docs/LICENSE.GPL
docs/LICENSE.txt
plonetheme/__init__.py
plonetheme.basic.egg-info/PKG-INFO
plonetheme.basic.egg-info/SOURCES.txt
plonetheme.basic.egg-info/dependency_links.txt
plonetheme.basic.egg-info/entry_points.txt
plonetheme.basic.egg-info/namespace_packages.txt
plonetheme.basic.egg-info/not-zip-safe
plonetheme.basic.egg-info/requires.txt
plonetheme.basic.egg-info/top_level.txt
plonetheme/basic/__init__.py
plonetheme/basic/configure.zcml
plonetheme/basic/tests.py
plonetheme/basic/profiles/default/cssregistry.xml
plonetheme/basic/profiles/default/jsregistry.xml
plonetheme/basic/profiles/default/metadata.xml
plonetheme/basic/profiles/default/skins.xml
plonetheme/basic/profiles/default/viewlets.xml
plonetheme/basic/profiles/uninstall/skins.xml
plonetheme/basic/skins/basic_images/CONTENT.txt
plonetheme/basic/skins/basic_images/logo.png
plonetheme/basic/skins/basic_images/pb_close.png
plonetheme/basic/skins/basic_styles/CONTENT.txt
plonetheme/basic/skins/basic_styles/authoring.css.dtml
plonetheme/basic/skins/basic_styles/base_properties.props
plonetheme/basic/skins/basic_styles/basic.js
plonetheme/basic/skins/basic_styles/ploneCustom.css.dtml
plonetheme/basic/skins/basic_styles/plonebasic_properties.props
plonetheme/basic/skins/basic_styles/portlets.css.dtml
plonetheme/basic/skins/basic_styles/print.css.dtml
plonetheme/basic/skins/basic_styles/public.css.dtml
plonetheme/basic/skins/basic_styles/visualeditor.css.dtml